generateApiKey/__init__.py
generateApiKey-0.4.7.dist-info/LICENSE
generateApiKey-0.4.7.dist-info/METADATA
generateApiKey-0.4.7.dist-info/WHEEL
generateApiKey-0.4.7.dist-info/top_level.txt
generateApiKey-0.4.7.dist-info/RECORD
