Metadata-Version: 2.1
Name: generateApiKey
Version: 0.4.7
Summary: This package provides a convenient way to generate API keys using a secret, seed, and an optional include keyword. The generated keys are unique and secure, making them suitable for use in a variety of applications
Home-page: https://github.com/nuhmanpk/generate-api-key
Author: Nuhman Pk
Author-email: nuhmanpk7@gmail.com
License: MIT
Project-URL: Documentation, https://github.com/nuhmanpk/generate-api-key/blob/main/README.md
Project-URL: Funding, https://github.com/sponsors/nuhmanpk
Project-URL: Source, https://github.com/nuhmanpk/generate-api-key/
Project-URL: Tracker, https://github.com/nuhmanpk/generate-api-key/issues
Platform: UNKNOWN
Classifier: Programming Language :: Python :: 3.9
Classifier: License :: OSI Approved :: MIT License
Classifier: Operating System :: OS Independent
Requires-Python: >=3.9
License-File: LICENSE
Requires-Dist: cryptography
